MANIFEST.in
README.md
license.txt
setup.py
GRobot.egg-info/PKG-INFO
GRobot.egg-info/SOURCES.txt
GRobot.egg-info/dependency_links.txt
GRobot.egg-info/not-zip-safe
GRobot.egg-info/requires.txt
GRobot.egg-info/top_level.txt
example/post_twitter.py
example/search_google.py
grobot/GRobot.py
grobot/TestDriver.py
grobot/__init__.py
grobot/javascripts/atoms.js
grobot/javascripts/find_matching_child.js
grobot/javascripts/htmlutils.js
grobot/javascripts/jquery-1.9.1.min.js
grobot/javascripts/selenium-api-override.js
grobot/javascripts/selenium-api.js
grobot/javascripts/selenium-browserbot.js
grobot/javascripts/selenium-browserdetect.js
grobot/javascripts/selenium-commandhandlers.js
grobot/javascripts/selenium-executionloop.js
grobot/javascripts/selenium-logging.js
grobot/javascripts/selenium-remoterunner.js
grobot/javascripts/selenium-testrunner-original.js
grobot/javascripts/selenium-testrunner.js
grobot/javascripts/selenium-version.js
grobot/javascripts/ui-element.js
grobot/javascripts/ui-map-sample.js
grobot/javascripts/user-extensions.js
grobot/javascripts/xmlextras.js
tests/__init__.py
tests/app.py
tests/run_test.py
tests/static/blackhat.jpg
tests/static/foo.tar.gz
tests/static/mootools.js
tests/templates/alert.html
tests/templates/form.html
tests/templates/home.html
tests/templates/image.html
tests/templates/mootools.html
tests/templates/settimeout.html
tests/templates/upload.html
tests/templates/url_hash.html