Metadata-Version: 1.1
Name: GRobot
Version: 0.0.13
Summary: Powerful Web Robot.
Home-page: https://github.com/DYFeng/GRobot
Author: DY.Feng
Author-email: yyfeng88625@gmail.com
License: MIT
Platform: any
Classifier: Development Status :: 4 - Beta
Classifier: Environment :: Web Environment
Classifier: Intended Audience :: Developers
Classifier: License :: OSI Approved :: MIT License
Classifier: Operating System :: OS Independent
Classifier: Programming Language :: Python
Classifier: Topic :: Internet :: WWW/HTTP :: Dynamic Content
Classifier: Topic :: Software Development :: Libraries :: Python Modules
